setup.py
airbrite/__init__.py
airbrite/api.py
airbrite.egg-info/PKG-INFO
airbrite.egg-info/SOURCES.txt
airbrite.egg-info/dependency_links.txt
airbrite.egg-info/requires.txt
airbrite.egg-info/top_level.txt
airbrite/tests/__init__.py
airbrite/tests/tests.py