Metadata-Version: 1.0
Name: airbrite
Version: 0.1
Summary: Airbrite python bindings
Home-page: https://www.airbrite.io/
Author: Elvio Toccalino
Author-email: etoccalino@creativa77.com.ar
License: UNKNOWN
Platform: UNKNOWN
